minha_biblioteca_gestor_saldo/__init__.py
minha_biblioteca_gestor_saldo/gestor_saldo.py
minha_biblioteca_gestor_saldo-0.1.0.dist-info/METADATA
minha_biblioteca_gestor_saldo-0.1.0.dist-info/WHEEL
minha_biblioteca_gestor_saldo-0.1.0.dist-info/top_level.txt
minha_biblioteca_gestor_saldo-0.1.0.dist-info/RECORD
