Metadata-Version: 2.4
Name: minha-biblioteca-gestor-saldo
Version: 0.1.0
Summary: Uma biblioteca com função de gestor de saldo, criada no curso de Python da Nersant
Author-email: Marcelo Kamei <marcelokamei78@gmail.com>
License: MIT
Requires-Python: >=3.8
